LICENSE
MANIFEST.in
README.rst
setup.py
docs/.DS_Store
docs/.changelog.rst.swp
docs/Makefile
docs/changelog.rst
docs/conf.py
docs/contents.rst.inc
docs/index.rst
docs/installation.rst
docs/integration.rst
docs/preparation.rst
docs/usage.rst
docs/_static/.gitignore
docs/_static/images/sp_logo.png
sphinxit/__init__.py
sphinxit.egg-info/PKG-INFO
sphinxit.egg-info/SOURCES.txt
sphinxit.egg-info/dependency_links.txt
sphinxit.egg-info/requires.txt
sphinxit.egg-info/top_level.txt
sphinxit/core/__init__.py
sphinxit/core/connector.py
sphinxit/core/constants.py
sphinxit/core/convertors.py
sphinxit/core/exceptions.py
sphinxit/core/helpers.py
sphinxit/core/mixins.py
sphinxit/core/nodes.py
sphinxit/core/processor.py
sphinxit/tests/__init__.py
sphinxit/tests/test_convertors.py
sphinxit/tests/test_core.py
sphinxit/tests/test_processor.py