Metadata-Version: 1.0
Name: sphinxit
Version: 0.3.2
Summary: Lite and powerful SphinxQL query constructor
Home-page: https://github.com/semirook/sphinxit
Author: Roman Semirook
Author-email: semirook@gmail.com
License: BSD
Platform: UNKNOWN
Classifier: Development Status :: 4 - Beta
Classifier: Intended Audience :: Developers
Classifier: License :: OSI Approved :: BSD License
Classifier: Operating System :: OS Independent
Classifier: Programming Language :: Python
Classifier: Programming Language :: Python :: 2.6
Classifier: Programming Language :: Python :: 2.7
Classifier: Programming Language :: Python :: 2 :: Only
Classifier: Topic :: Software Development :: Libraries :: Python Modules
